MANIFEST.in
README.md
setup.py
Jeev.egg-info/PKG-INFO
Jeev.egg-info/SOURCES.txt
Jeev.egg-info/dependency_links.txt
Jeev.egg-info/not-zip-safe
Jeev.egg-info/requires.txt
Jeev.egg-info/top_level.txt
bin/jeev
jeev/__init__.py
jeev/jeev.py
jeev/message.py
jeev/module.py
jeev/web.py
jeev.egg-info/SOURCES.txt
jeev/adapter/__init__.py
jeev/adapter/console.py
jeev/adapter/slack.py
jeev/starter_template/.gitignore
jeev/starter_template/config.py
jeev/starter_template/requirements.txt
jeev/starter_template/modules/__init__.py
jeev/starter_template/modules/sample.py
jeev/storage/__init__.py
jeev/storage/ephemeral.py
jeev/storage/redis.py
jeev/storage/shelve.py
jeev/utils/__init__.py
jeev/utils/date.py
jeev/utils/env.py
jeev/utils/g.py
jeev/utils/importing.py
jeev/utils/periodic.py