Metadata-Version: 1.1
Name: jeev
Version: 0.1.0
Summary: A simple chat bot, at your service.
Home-page: https://github.com/jhgg/jeev
Author: Jacob Heinz
Author-email: me@jh.gg
License: MIT
Keywords: chat slack bot irc jeev
Platform: UNKNOWN
Classifier: Development Status :: 4 - Beta
Classifier: Topic :: Communications :: Chat
Classifier: Topic :: Utilities
Classifier: Framework :: Flask
Classifier: License :: OSI Approved :: MIT License
Classifier: Programming Language :: Python :: 2.7
Classifier: Programming Language :: Python :: 2 :: Only
Classifier: License :: OSI Approved :: MIT License
